{
    "toggleServiceHotkey": {
        "modifiers": [
            "<shift>",
            "<super>"
        ],
        "enabled": true,
        "hotKey": "k"
    },
    "userCodeDir": "/home/ern6xv/.config/autokey/data/lib",
    "configHotkey": {
        "modifiers": [
            "<super>"
        ],
        "enabled": true,
        "hotKey": "k"
    },
    "folders": [],
    "version": "0.93.10",
    "settings": {
        "workAroundApps": ".*VirtualBox.*|krdc.Krdc",
        "serviceRunning": true,
        "columnWidths": [
            150,
            50,
            100
        ],
        "hPanePosition": 489,
        "scriptGlobals": {},
        "notificationIcon": "autokey-status",
        "triggerItemByInitial": false,
        "enableQT4Workaround": false,
        "windowDefaultSize": [
            1600,
            978
        ],
        "menuTakesFocus": false,
        "isFirstRun": true,
        "interfaceType": "XRecord",
        "sortByUsageCount": true,
        "promptToSave": false,
        "showToolbar": true,
        "undoUsingBackspace": true,
        "showTrayIcon": true
    }
}