{
    "version": "0.93.10",
    "settings": {
        "undoUsingBackspace": true,
        "interfaceType": "XRecord",
        "menuTakesFocus": false,
        "triggerItemByInitial": false,
        "windowDefaultSize": [
            1600,
            870
        ],
        "promptToSave": false,
        "showToolbar": true,
        "isFirstRun": true,
        "enableQT4Workaround": false,
        "showTrayIcon": true,
        "sortByUsageCount": true,
        "serviceRunning": true,
        "scriptGlobals": {},
        "workAroundApps": ".*VirtualBox.*|krdc.Krdc",
        "columnWidths": [
            150,
            50,
            100
        ],
        "hPanePosition": 543,
        "notificationIcon": "autokey-status"
    },
    "configHotkey": {
        "hotKey": "k",
        "enabled": true,
        "modifiers": [
            "<super>"
        ]
    },
    "userCodeDir": "/home/ern6xv/.config/autokey/data/lib",
    "toggleServiceHotkey": {
        "hotKey": "k",
        "enabled": true,
        "modifiers": [
            "<shift>",
            "<super>"
        ]
    },
    "folders": []
}